torrent2magnet/__init__.py
torrent2magnet/example.py
torrent2magnet-0.0.1.dist-info/METADATA
torrent2magnet-0.0.1.dist-info/WHEEL
torrent2magnet-0.0.1.dist-info/top_level.txt
torrent2magnet-0.0.1.dist-info/RECORD
