Metadata-Version: 2.1
Name: torrent2magnet
Version: 0.0.1
Summary: 分析 btbtt.com 網址，批量轉成 magnet。
Author-email: MiNG TSE <m@ming.club>
Project-URL: Homepage, https://github.com/tsmhome
Project-URL: Bug Tracker, https://github.com/tsmhome/torrent2magnet
Classifier: Programming Language :: Python :: 3
Classifier: License :: OSI Approved :: MIT License
Classifier: Operating System :: OS Independent
Requires-Python: >=3.7
